{
  "Routes": [
    {
      "DownstreamPathTemplate": "/api/auth/{everything}",
      "DownstreamScheme": "http",
      "DownstreamHostAndPorts": [
        {
          "Host": "authservice",
          "Port": 5112
        }
      ],
      "UpstreamPathTemplate": "/api/auth/{everything}",
      "UpstreamHttpMethod": [ "GET", "POST", "PUT", "DELETE" ]
    },
    {
      "DownstreamPathTemplate": "/api/cart/{everything}",
      "DownstreamScheme": "http",
      "DownstreamHostAndPorts": [
        {
          "Host": "cartservice",
          "Port": 5236
        }
      ],
      "UpstreamPathTemplate": "/api/cart/{everything}",
      "UpstreamHttpMethod": [ "GET", "POST", "PUT", "DELETE" ]
    }
  ],
  "GlobalConfiguration": {
    "BaseUrl": "http://apigateway:5157"
  }

}
